keios_protocol_pocketsphinx/__init__.py
keios_protocol_pocketsphinx/flatbuffers/Guess.py
keios_protocol_pocketsphinx/flatbuffers/PocketSphinxMessage.py
keios_protocol_pocketsphinx/flatbuffers/PocketSphinxMessageType.py
keios_protocol_pocketsphinx/flatbuffers/PocketSphinxRequest.py
keios_protocol_pocketsphinx/flatbuffers/PocketSphinxResponse.py
keios_protocol_pocketsphinx/flatbuffers/PocketsphinxRequest.py
keios_protocol_pocketsphinx/flatbuffers/PocketsphinxResponse.py
keios_protocol_pocketsphinx-0.3.0.dist-info/WHEEL
keios_protocol_pocketsphinx-0.3.0.dist-info/METADATA
keios_protocol_pocketsphinx-0.3.0.dist-info/RECORD
